myeasygui/__init__.py
myeasygui/boxes/Errorbox.py
myeasygui/boxes/Warningbox.py
myeasygui/boxes/__init__.py
myeasygui/boxes/directorybox.py
myeasygui/boxes/enterbox.py
myeasygui/boxes/fileopenbox.py
myeasygui/boxes/filesavesbox.py
myeasygui/boxes/msgbox.py
myeasygui/boxes/okcancelbox.py
myeasygui/boxes/passwordbox.py
myeasygui/boxes/questionbox.py
myeasygui/boxes/retrycancelbox.py
myeasygui/boxes/textbox.py
myeasygui/boxes/userpasswordbox.py
myeasygui/boxes/yesnobox.py
myeasygui/boxes/yesnocancelbox.py
myeasygui-0.0.0.2.dist-info/METADATA
myeasygui-0.0.0.2.dist-info/WHEEL
myeasygui-0.0.0.2.dist-info/top_level.txt
myeasygui-0.0.0.2.dist-info/RECORD
