Metadata-Version: 2.1
Name: myeasygui
Version: 0.0.0.2
Summary: this is a test project
Home-page: 
Author: Yvan
Author-email: yvan_chen2022@163.com
License: MIT
